distriremesaparser/__init__.py
distriremesaparser/csvparser.py
distriremesaparser/xlsparser.py
distri_remesa_parser-0.1.6.dist-info/LICENSE
distri_remesa_parser-0.1.6.dist-info/METADATA
distri_remesa_parser-0.1.6.dist-info/WHEEL
distri_remesa_parser-0.1.6.dist-info/top_level.txt
distri_remesa_parser-0.1.6.dist-info/RECORD
